pychoropleth/__init__.py
pychoropleth-0.2.3.dist-info/LICENSE
pychoropleth-0.2.3.dist-info/METADATA
pychoropleth-0.2.3.dist-info/WHEEL
pychoropleth-0.2.3.dist-info/top_level.txt
pychoropleth-0.2.3.dist-info/RECORD
